BHCAA/BHC.py
BHCAA/BHC_Examples.py
BHCAA/BHC_Opt.py
BHCAA/__init__.py
BHCAA-0.1.dist-info/LICENSE
BHCAA-0.1.dist-info/METADATA
BHCAA-0.1.dist-info/WHEEL
BHCAA-0.1.dist-info/top_level.txt
BHCAA-0.1.dist-info/RECORD
