Metadata-Version: 2.1
Name: BHCAA
Version: 0.1
Summary: Bayesian Hierachichal Clustering using Heller's article
Home-page: https://github.com/AzucenaMV/STAT-663
Author: Azucena Morales<lm348@duke.edu>, Alan Zhou<zz161@duke.edu>
Author-email: alanazu@googlegroups.com
License: UNKNOWN
Platform: UNKNOWN
Classifier: Programming Language :: Python :: 3
Classifier: License :: OSI Approved :: MIT License
Classifier: Operating System :: OS Independent
